{"textures": {"layer0": "spartanlands:items/crossbow_weedwood_standby"}, "overrides": [{"predicate": {"pulling": 1}, "model": "spartanlands:item/crossbow_weedwood_pulling_0"}, {"predicate": {"pull": 0.65, "pulling": 1}, "model": "spartanlands:item/crossbow_weedwood_pulling_1"}, {"predicate": {"pull": 0.9, "pulling": 1}, "model": "spartanlands:item/crossbow_weedwood_pulling_2"}, {"predicate": {"pull": 1.0, "pulling": 0}, "model": "spartanlands:item/crossbow_weedwood_loaded"}, {"predicate": {"pull": 1.0, "pulling": 1}, "model": "spartanlands:item/crossbow_weedwood_firing"}], "parent": "spartanweaponry:item/crossbow_wood"}